pydroneapi/__init__.py
pydroneapi/main.py
pydroneapi-0.1.2.dist-info/LICENSE
pydroneapi-0.1.2.dist-info/METADATA
pydroneapi-0.1.2.dist-info/WHEEL
pydroneapi-0.1.2.dist-info/top_level.txt
pydroneapi-0.1.2.dist-info/RECORD
