Metadata-Version: 2.1
Name: pydroneapi
Version: 0.1.2
Summary: Helper scripts to manage Drone API operations
Home-page: https://github.com/bellyjay1005/pydroneci
Author: Jelili Adebello
Author-email: jeliliadebello@gmail.com
License: MIT
Download-URL: https://github.com/bellyjay1005/pydroneci/archive/refs/tags/v0.1.0.tar.gz
Platform: UNKNOWN
Classifier: Development Status :: 3 - Alpha
Classifier: Intended Audience :: Developers
Classifier: Topic :: Software Development :: Build Tools
Classifier: License :: OSI Approved :: MIT License
Classifier: Programming Language :: Python :: 3
Classifier: Operating System :: OS Independent
Requires-Python: >=3.6
Requires-Dist: boto3
Requires-Dist: requests
Provides-Extra: dev
Requires-Dist: PyYAML (>=5.3.1) ; extra == 'dev'
Requires-Dist: pylint (>=2.5.0) ; extra == 'dev'
Requires-Dist: pytest (>=5.4.1) ; extra == 'dev'
Requires-Dist: pytest-cov (>=2.8.1) ; extra == 'dev'
Requires-Dist: bandit (>=1.6.2) ; extra == 'dev'
Requires-Dist: safety (>=1.10.3) ; extra == 'dev'
Requires-Dist: requests-mock ; extra == 'dev'
